localgrid/__init__.py
localgrid/core.py
localgrid/mappings.py
localgrid/data/__init__.py
localgrid/data/localgrid_cache.json
localgrid/tokenizers/__init__.py
localgrid/tokenizers/all-minilm/LICENSE
localgrid/tokenizers/all-minilm/special_tokens_map.json
localgrid/tokenizers/all-minilm/tokenizer.json
localgrid/tokenizers/all-minilm/tokenizer_config.json
localgrid/tokenizers/all-minilm/vocab.txt
localgrid/tokenizers/aya/LICENSE
localgrid/tokenizers/aya/tokenizer.json
localgrid/tokenizers/aya/tokenizer_config.json
localgrid/tokenizers/bge/LICENSE
localgrid/tokenizers/bge/special_tokens_map.json
localgrid/tokenizers/bge/tokenizer.json
localgrid/tokenizers/bge/tokenizer_config.json
localgrid/tokenizers/dbrx/LICENSE
localgrid/tokenizers/dbrx/added_tokens.json
localgrid/tokenizers/dbrx/merges.txt
localgrid/tokenizers/dbrx/special_tokens_map.json
localgrid/tokenizers/dbrx/tokenizer.json
localgrid/tokenizers/dbrx/tokenizer_config.json
localgrid/tokenizers/dbrx/vocab.json
localgrid/tokenizers/deepseek/LICENSE
localgrid/tokenizers/deepseek/tokenizer.json
localgrid/tokenizers/deepseek/tokenizer_config.json
localgrid/tokenizers/ernie/LICENSE
localgrid/tokenizers/ernie/special_tokens_map.json
localgrid/tokenizers/ernie/tokenizer.json
localgrid/tokenizers/ernie/tokenizer.model
localgrid/tokenizers/ernie/tokenizer_config.json
localgrid/tokenizers/exaone/LICENSE
localgrid/tokenizers/exaone/merges.txt
localgrid/tokenizers/exaone/special_tokens_map.json
localgrid/tokenizers/exaone/tokenizer.json
localgrid/tokenizers/exaone/tokenizer_config.json
localgrid/tokenizers/exaone/vocab.json
localgrid/tokenizers/falcon/LICENSE
localgrid/tokenizers/falcon/special_tokens_map.json
localgrid/tokenizers/falcon/tokenizer.json
localgrid/tokenizers/falcon/tokenizer_config.json
localgrid/tokenizers/gemma/LICENSE
localgrid/tokenizers/gemma/special_tokens_map.json
localgrid/tokenizers/gemma/tokenizer.json
localgrid/tokenizers/gemma/tokenizer.model
localgrid/tokenizers/gemma/tokenizer_config.json
localgrid-0.1.0.dist-info/LICENSE
localgrid-0.1.0.dist-info/METADATA
localgrid-0.1.0.dist-info/WHEEL
localgrid-0.1.0.dist-info/top_level.txt
localgrid-0.1.0.dist-info/RECORD
