Metadata-Version: 2.1
Name: localgrid
Version: 0.1.0
Summary: A library for inspecting local LLM providers and tokenizers.
Author-email: Alan Mackiewicz <alanmackiewicz03@gmail.com>
License: MIT License
Project-URL: Homepage, https://github.com/AlanM03/LocalGrid
Project-URL: Source, https://github.com/AlanM03/LocalGrid
Classifier: Programming Language :: Python :: 3
Classifier: License :: OSI Approved :: MIT License
Classifier: Operating System :: OS Independent
Classifier: Intended Audience :: Developers
Classifier: Topic :: Software Development :: Libraries :: Python Modules
Classifier: Topic :: Scientific/Engineering :: Artificial Intelligence
Requires-Python: >=3.8
License-File: LICENSE
Requires-Dist: tiktoken
Requires-Dist: httpx
Requires-Dist: transformers
Requires-Dist: protobuf
Requires-Dist: sentencepiece
Provides-Extra: dev
Requires-Dist: ruff ; extra == 'dev'
Requires-Dist: pytest ; extra == 'dev'
Requires-Dist: pytest-asyncio ; extra == 'dev'
Requires-Dist: pytest-mock ; extra == 'dev'
Requires-Dist: anyio ; extra == 'dev'
